manychat_mcp_server/ManyChatPage.py
manychat_mcp_server/__init__.py
manychat_mcp_server/__main__.py
manychat_mcp_server/manychat.py
manychat_mcp_server/server.py
manychat_mcp_server-0.1.11.dist-info/METADATA
manychat_mcp_server-0.1.11.dist-info/WHEEL
manychat_mcp_server-0.1.11.dist-info/entry_points.txt
manychat_mcp_server-0.1.11.dist-info/top_level.txt
manychat_mcp_server-0.1.11.dist-info/RECORD
