Metadata-Version: 2.4
Name: manychat-mcp-server
Version: 0.1.11
Summary: A FastMCP-based server that integrates with ManyChat to send Instagram messages and call-button actions using async APIs and secure environment-based configuration.
Author-email: Venkatesh M <venkateshvenki404224@gmail.com>
Requires-Python: >=3.12
Requires-Dist: httpx>=0.28.1
Requires-Dist: mcp[cli]>=1.6.0
Requires-Dist: python-dotenv
